LICENSE
MANIFEST.in
README.md
setup.py
jsonuri/__init__.py
jsonuri/io.py
jsonuri/jsonuri.py
jsonuri.egg-info/PKG-INFO
jsonuri.egg-info/SOURCES.txt
jsonuri.egg-info/dependency_links.txt
jsonuri.egg-info/requires.txt
jsonuri.egg-info/top_level.txt