Metadata-Version: 1.1
Name: jsonuri
Version: 0.2.2
Summary: This package helps you convert Python dictionaries into an Gzip compressed, Base64 string for use as a HTTP GET request parameter and reverse it
Home-page: https://github.com/guidj/jsonuri-py
Author: guilherme
Author-email: guilherme.dinisjunior@gmail.com
License: Apache License, Version 2.0
Platform: UNKNOWN
Classifier: Programming Language :: Python :: 3.6
Classifier: Intended Audience :: Developers
Classifier: License :: OSI Approved :: Apache Software License
Classifier: Operating System :: OS Independent
Classifier: Topic :: Software Development
